LICENSE
MANIFEST.in
README.md
ringmaster.py
setup.cfg
setup.py
ringmaster.egg-info/PKG-INFO
ringmaster.egg-info/SOURCES.txt
ringmaster.egg-info/dependency_links.txt
ringmaster.egg-info/entry_points.txt
ringmaster.egg-info/requires.txt
ringmaster.egg-info/top_level.txt