Metadata-Version: 1.1
Name: ringmaster
Version: 0.4.0
Summary: Circus Tcl/Tk Control Panel
Home-page: https://github.com/viotti/ringmaster
Author: Rafael Viotti
Author-email: rviotti@gmail.com
License: UNKNOWN
Download-URL: https://github.com/viotti/ringmaster/tarball/0.2.0
Platform: UNKNOWN
